TelegramBot8/TeleBot.py
TelegramBot8/__init__.py
TelegramBot8/Exception/CommandException.py
TelegramBot8/Exception/__init__.py
TelegramBot8/Handlers/CommandHandler.py
TelegramBot8/Handlers/__init__.py
TelegramBot8/Model/__init__.py
TelegramBot8/Model/Dto/CallBackMessage.py
TelegramBot8/Model/Dto/Chat.py
TelegramBot8/Model/Dto/Constants.py
TelegramBot8/Model/Dto/Entities.py
TelegramBot8/Model/Dto/Keyboard.py
TelegramBot8/Model/Dto/User.py
TelegramBot8/Model/Dto/__init__.py
TelegramBot8/Model/Reqest/Base.py
TelegramBot8/Model/Reqest/CommandRequest.py
TelegramBot8/Model/Reqest/ForwardReqest.py
TelegramBot8/Model/Reqest/MediaRequest.py
TelegramBot8/Model/Reqest/MessageRequest.py
TelegramBot8/Model/Reqest/UrlRequest.py
TelegramBot8/Model/Reqest/__init__.py
TelegramBot8/Model/Response/BaseConvertors.py
TelegramBot8/Model/Response/BaseResponse.py
TelegramBot8/Model/Response/ForwardResponse.py
TelegramBot8/Model/Response/GetMeResponse.py
TelegramBot8/Model/Response/MediaResponse.py
TelegramBot8/Model/Response/Response.py
TelegramBot8/Model/Response/UpdateResponse.py
TelegramBot8/Model/Response/__init__.py
test/BotTest.py
test/__init__.py
Telegram_Bot8-0.2.6.dist-info/LICENSE
Telegram_Bot8-0.2.6.dist-info/METADATA
Telegram_Bot8-0.2.6.dist-info/WHEEL
Telegram_Bot8-0.2.6.dist-info/top_level.txt
Telegram_Bot8-0.2.6.dist-info/RECORD
