Metadata-Version: 2.1
Name: Telegram-Bot8
Version: 0.2.6
Summary: Python package to utilizes the telegram API to easily add commands and person other actions
Home-page: https://github.com/AppDevIn/TelegramBot
Author: AppDevIn Sliver
Author-email:  teamprojectlive@gmail.com
License: UNKNOWN
Project-URL: Bug Tracker, https://github.com/AppDevIn/TelegramBot/issues
Platform: UNKNOWN
Classifier: Programming Language :: Python :: 3
Classifier: License :: OSI Approved :: MIT License
Classifier: Operating System :: OS Independent
Requires-Python: >=3.6
License-File: LICENSE
